{
  "status": "success",
  "data": [
    {
      "type": "tvshows",
      "title": "Brincando com Fogo: América Latina",
      "permalink": "https://thefilmes.tv/series/131589-brincando-com-fogo-america-latina/",
      "category": "Lançamento, Reality",
      "imdb": "tt15251764",
      "poster": "https://image.tmdb.org/t/p/w300/bkxa5Q3cMml5zIYJ2r1J4poqRMX.jpg",
      "backdrop": "https://image.tmdb.org/t/p/w500/65sKzxSkfIie8bqY6wHHkBCQyEU.jpg",
      "year": "2021",
      "imdbRating": "10",
      "runtime": "",
      "episode": "8"
    },
    {
      "type": "tvshows",
      "title": "Tattoo Fail",
      "permalink": "https://thefilmes.tv/series/128254-tattoo-fail/",
      "category": "Lançamento, Reality",
      "imdb": "tt14956090",
      "poster": "https://image.tmdb.org/t/p/w300/b0LIMiV3iLWgmBONEc7AC1YvyC.jpg",
      "backdrop": "https://image.tmdb.org/t/p/w500/knfCNmBIMGotuctiY2PrKphzpaC.jpg",
      "year": "2021",
      "imdbRating": "6",
      "runtime": "30",
      "episode": "6"
    },
    {
      "type": "tvshows",
      "title": "Lockdown Americano \u0026amp; Desbancando Borat",
      "permalink": "https://thefilmes.tv/series/126326-lockdown-americano-desbancando-borat/",
      "category": "Comédia, Lançamento, Reality",
      "imdb": "tt14532380",
      "poster": "https://image.tmdb.org/t/p/w300/9W7zYf8MIEYGYuL8KkHwAh9KDjV.jpg",
      "backdrop": "https://image.tmdb.org/t/p/w500/vh4d1cuYP8XawKe5Up1KnqLjbSJ.jpg",
      "year": "2021",
      "imdbRating": "6.3",
      "runtime": "7",
      "episode": "7"
    },
    {
      "type": "tvshows",
      "title": "Como Virar um Cowboy",
      "permalink": "https://thefilmes.tv/series/132012-como-virar-um-cowboy/",
      "category": "Lançamento, Reality",
      "imdb": "tt13438900",
      "poster": "https://image.tmdb.org/t/p/w300/kJjlR9PPU4vIUI1rzqXlKSD3oaO.jpg",
      "backdrop": "https://image.tmdb.org/t/p/w500/lWcRwNF4ekO54AYkBghkX6Jizms.jpg",
      "year": "2021",
      "imdbRating": "10",
      "runtime": "25",
      "episode": "6"
    },
    {
      "type": "tvshows",
      "title": "RuPaul\u0026#8217;s Drag Race All Stars",
      "permalink": "https://thefilmes.tv/series/67482-rupauls-drag-race-all-stars/",
      "category": "Reality",
      "imdb": "tt2301351",
      "poster": "https://image.tmdb.org/t/p/w300/nQ6MjgKPujYPRQkwP7KoZe349GC.jpg",
      "backdrop": "https://image.tmdb.org/t/p/w500/eTatUUpMXfLNgNesL1jvQ1EQ9Q2.jpg",
      "year": "2012",
      "imdbRating": "8.4",
      "runtime": "43",
      "episode": "6"
    },
    {
      "type": "tvshows",
      "title": "Brincando com Fogo: Brasil",
      "permalink": "https://thefilmes.tv/series/128251-brincando-com-fogo-brasil/",
      "category": "Lançamento, Reality",
      "imdb": "tt14902484",
      "poster": "https://image.tmdb.org/t/p/w300/oVvwzG5S3SO7cF74xi1eLGlSDY5.jpg",
      "backdrop": "https://image.tmdb.org/t/p/w500/itrXSnT99YnFvmHRWbWBDvdwJvh.jpg",
      "year": "2021",
      "imdbRating": "",
      "runtime": "",
      "episode": "4"
    },
    {
      "type": "tvshows",
      "title": "Vida de Madeireiro",
      "permalink": "https://thefilmes.tv/series/114992-vida-de-madeireiro/",
      "category": "Lançamento, Reality",
      "imdb": "tt13322572",
      "poster": "https://image.tmdb.org/t/p/w300/2bHXPiYsaFGncSqJAwttsiEAUtw.jpg",
      "backdrop": "https://image.tmdb.org/t/p/w500/rwZ1JS2Q4k6vQYfUE1L4Y8ZLfGm.jpg",
      "year": "2020",
      "imdbRating": "6",
      "runtime": "45",
      "episode": "10"
    },
    {
      "type": "tvshows",
      "title": "Crazy Delicious",
      "permalink": "https://thefilmes.tv/series/105125-crazy-delicious/",
      "category": "Lançamento, Reality",
      "imdb": "tt11301834",
      "poster": "https://image.tmdb.org/t/p/w300/altQjpJCcwGpiW453jWoAPZMj15.jpg",
      "backdrop": "https://image.tmdb.org/t/p/w500/zcje7Y0QwDSCE5p88x6IQj37bWV.jpg",
      "year": "2020",
      "imdbRating": "10",
      "runtime": "47",
      "episode": "6"
    },
    {
      "type": "tvshows",
      "title": "Os Mestres da Fritura",
      "permalink": "https://thefilmes.tv/series/125629-os-mestres-da-fritura/",
      "category": "Lançamento, Reality",
      "imdb": "tt14644428",
      "poster": "https://image.tmdb.org/t/p/w300/xSFAHhvlETqE3PVqGxgtAgwvem3.jpg",
      "backdrop": "https://image.tmdb.org/t/p/w500/sm4Cy6sSTFQzhOEDwVoUFqWU7ok.jpg",
      "year": "2021",
      "imdbRating": "",
      "runtime": "",
      "episode": "8"
    },
    {
      "type": "tvshows",
      "title": "The Voice",
      "permalink": "https://thefilmes.tv/series/37678-the-voice/",
      "category": "Música, Reality",
      "imdb": "tt1839337",
      "poster": "https://image.tmdb.org/t/p/w300/5bAzxOZRliSNyuGj3xdVgBLaPup.jpg",
      "backdrop": "https://image.tmdb.org/t/p/w500/nRcPtIn39NEKCavn7S4wkO0WrwB.jpg",
      "year": "2011",
      "imdbRating": "5.5",
      "runtime": "43",
      "episode": "18"
    },
    {
      "type": "tvshows",
      "title": "Quem Casa Quer Casa",
      "permalink": "https://thefilmes.tv/series/119151-quem-casa-quer-casa/",
      "category": "Lançamento, Reality",
      "imdb": "tt14037542",
      "poster": "https://image.tmdb.org/t/p/w300/n8uSkOS7t1MT3XVGy6jufqlOr8Q.jpg",
      "backdrop": "https://image.tmdb.org/t/p/w500/iTNHxofeVgtzAoFMz5SSQn4jOTO.jpg",
      "year": "2021",
      "imdbRating": "10",
      "runtime": "40",
      "episode": "10"
    },
    {
      "type": "tvshows",
      "title": "Mágica para a Humanidade: Espanha",
      "permalink": "https://thefilmes.tv/series/121424-magica-para-a-humanidade-espanha/",
      "category": "Comédia, Lançamento, Reality",
      "imdb": "tt14136320",
      "poster": "https://image.tmdb.org/t/p/w300/rBRltGYFyxWXKMJBi9TobW5b4W8.jpg",
      "backdrop": "https://image.tmdb.org/t/p/w500/18rNLGHCcKsxbji7zdCBW6fiqUb.jpg",
      "year": "2021",
      "imdbRating": "5.3",
      "runtime": "",
      "episode": "6"
    },
    {
      "type": "tvshows",
      "title": "Stanley Tucci: Searching for Italy",
      "permalink": "https://thefilmes.tv/series/119033-stanley-tucci-searching-for-italy/",
      "category": "Documentário, Lançamento, Reality",
      "imdb": "tt11852724",
      "poster": "https://image.tmdb.org/t/p/w300/5M9FuXgBTE7LYDeHvYNVgEupXJW.jpg",
      "backdrop": "https://image.tmdb.org/t/p/w500/4oD57zQlpCoUuVq0wm076ZWFIVx.jpg",
      "year": "2021",
      "imdbRating": "9.5",
      "runtime": "45",
      "episode": "6"
    },
    {
      "type": "tvshows",
      "title": "Eu Vi: América Latina",
      "permalink": "https://thefilmes.tv/series/120587-eu-vi-america-latina/",
      "category": "Lançamento, Reality",
      "imdb": "tt14164238",
      "poster": "https://image.tmdb.org/t/p/w300/Q1ZYG3kDS8iVIHOYOJ9NQmV0q7.jpg",
      "backdrop": "https://image.tmdb.org/t/p/w500/lEZLrd3N9nIk5fnCL30GsboCEmB.jpg",
      "year": "2021",
      "imdbRating": "7.5",
      "runtime": "30",
      "episode": "5"
    },
    {
      "type": "tvshows",
      "title": "Pet Stars",
      "permalink": "https://thefilmes.tv/series/121629-pet-stars/",
      "category": "Família, Lançamento, Reality",
      "imdb": "tt14318392",
      "poster": "https://image.tmdb.org/t/p/w300/lnQq2dXQGqen58jBTkrT4z40Erk.jpg",
      "backdrop": "https://image.tmdb.org/t/p/w500/m592cjYFNIDlKEcRzF7vT5hGcCD.jpg",
      "year": "2021",
      "imdbRating": "8",
      "runtime": "29",
      "episode": "5"
    },
    {
      "type": "tvshows",
      "title": "Febre do Ouro",
      "permalink": "https://thefilmes.tv/series/34634-febre-do-ouro/",
      "category": "Reality",
      "imdb": "tt1800864",
      "poster": "https://image.tmdb.org/t/p/w300/t7sj18MvyNEKcPEssw3LngX6Ewl.jpg",
      "backdrop": "https://image.tmdb.org/t/p/w500/7RcfuY28JNdQKyBfiCmYniqdjw5.jpg",
      "year": "2010",
      "imdbRating": "6.9",
      "runtime": "41",
      "episode": "19"
    },
    {
      "type": "tvshows",
      "title": "Meu Amor: Seis Histórias de Amor Verdadeiro",
      "permalink": "https://thefilmes.tv/series/50016-meu-amor-seis-historias-de-amor-verdadeiro/",
      "category": "Documentário, Lançamento, Reality",
      "imdb": "tt14267526",
      "poster": "https://image.tmdb.org/t/p/w300/lzWNo5qRRvZ0SkmoFgnJ62EtMk.jpg",
      "backdrop": "https://image.tmdb.org/t/p/w500/cYAKFkw8mQPkBSoU1pxdMrHQlFh.jpg",
      "year": "2021",
      "imdbRating": "",
      "runtime": "",
      "episode": "6"
    },
    {
      "type": "tvshows",
      "title": "De Férias com o Ex Brasil",
      "permalink": "https://thefilmes.tv/series/68603-de-ferias-com-o-ex-brasil/",
      "category": "Reality",
      "imdb": "tt8470764",
      "poster": "https://image.tmdb.org/t/p/w300/9aBYWnwd86ejV4ic36z188ZiGu4.jpg",
      "backdrop": "https://image.tmdb.org/t/p/w500/zfuwv9hW3ZdUnOLyiYjtI51Suba.jpg",
      "year": "2016",
      "imdbRating": "9.5",
      "runtime": "60",
      "episode": "12"
    },
    {
      "type": "tvshows",
      "title": "Casamento sem Filtro",
      "permalink": "https://thefilmes.tv/series/122249-casamento-sem-filtro/",
      "category": "Comédia, Lançamento, Reality",
      "imdb": "tt14210424",
      "poster": "https://image.tmdb.org/t/p/w300/evQbhMe2QGgsAzcIjao0Uvm2Xsa.jpg",
      "backdrop": "https://image.tmdb.org/t/p/w500/BvDJdSDzMRkHxGhaLXTvX0xx5X.jpg",
      "year": "2021",
      "imdbRating": "10",
      "runtime": "",
      "episode": "6"
    },
    {
      "type": "tvshows",
      "title": "A Indústria da Cura",
      "permalink": "https://thefilmes.tv/series/106530-a-industria-da-cura/",
      "category": "Documentário, Lançamento, Reality",
      "imdb": "tt12759384",
      "poster": "https://image.tmdb.org/t/p/w300/bC1CSudFJCvDm679fRtqdVHlDc3.jpg",
      "backdrop": "https://image.tmdb.org/t/p/w500/fhIUJF2MpFoFXLCEErOIEuucqRi.jpg",
      "year": "2020",
      "imdbRating": "6.8",
      "runtime": "55",
      "episode": "6"
    },
    {
      "type": "tvshows",
      "title": "Casa Pronta Para o Natal",
      "permalink": "https://thefilmes.tv/series/112869-casa-pronta-para-o-natal/",
      "category": "Lançamento, Reality",
      "imdb": "tt13255112",
      "poster": "https://image.tmdb.org/t/p/w300/1SvpzeRMcYZpftWDgRIZEWFZnj4.jpg",
      "backdrop": "https://image.tmdb.org/t/p/w500/9Cn8uAyIdD20ifCROwpRIRsIAuM.jpg",
      "year": "2020",
      "imdbRating": "6.9",
      "runtime": "41",
      "episode": "4"
    },
    {
      "type": "tvshows",
      "title": "Dando um Tempo com Bert Kreischer",
      "permalink": "https://thefilmes.tv/series/110512-dando-um-tempo-com-bert-kreischer/",
      "category": "Comédia, Reality",
      "imdb": "tt11860180",
      "poster": "https://image.tmdb.org/t/p/w300/6pGq8TMpkmFjK33tiiOtRWbtHX4.jpg",
      "backdrop": "https://image.tmdb.org/t/p/w500/kotdWTTLFEcXDkUvG6agnoKPerj.jpg",
      "year": "2020",
      "imdbRating": "9",
      "runtime": "",
      "episode": "5"
    },
    {
      "type": "tvshows",
      "title": "Keeping Up With the Kardashians",
      "permalink": "https://thefilmes.tv/series/14814-keeping-up-with-the-kardashians/",
      "category": "Reality",
      "imdb": "tt1086761",
      "poster": "https://image.tmdb.org/t/p/w300/tnwtQMHGP0pCAWaAuKvXYewOAwX.jpg",
      "backdrop": "https://image.tmdb.org/t/p/w500/qnTBxxv7q4xVwgZBLb0vtILLelh.jpg",
      "year": "2007",
      "imdbRating": "4.7",
      "runtime": "42",
      "episode": "19"
    },
    {
      "type": "tvshows",
      "title": "Dinheiro à Mesa",
      "permalink": "https://thefilmes.tv/series/81660-dinheiro-a-mesa/",
      "category": "Reality",
      "imdb": "tt8488494",
      "poster": "https://image.tmdb.org/t/p/w300/l81uRo1MwUZgcUuFDnUJIx2adFE.jpg",
      "backdrop": "https://image.tmdb.org/t/p/w500/3rfZz7sPV6mDxMNMoO96afrJdkI.jpg",
      "year": "2018",
      "imdbRating": "7.6",
      "runtime": "60",
      "episode": "6"
    },
    {
      "type": "tvshows",
      "title": "A Bizarra Confeitaria de Christine McConnell",
      "permalink": "https://thefilmes.tv/series/81284-a-bizarra-confeitaria-de-christine-mcconnell/",
      "category": "Comédia, Reality, Talk",
      "imdb": "tt8773080",
      "poster": "https://image.tmdb.org/t/p/w300/A8yLoz3Mh8AjUZ2FgCYw3FKlevL.jpg",
      "backdrop": "https://image.tmdb.org/t/p/w500/eXHfjm2bz15XJNlNg6JZ3Rmjlxu.jpg",
      "year": "2018",
      "imdbRating": "7.3",
      "runtime": "30",
      "episode": "6"
    },
    {
      "type": "tvshows",
      "title": "Midas do Ferro-Velho",
      "permalink": "https://thefilmes.tv/series/82357-midas-do-ferro-velho/",
      "category": "Reality",
      "imdb": "tt8893550",
      "poster": "https://image.tmdb.org/t/p/w300/2p6LMKguFBS1z1dT67fwOrkG4Ao.jpg",
      "backdrop": "https://image.tmdb.org/t/p/w500/7Mf5BXqH7qeW2KZZtFwe6XUY7ul.jpg",
      "year": "2018",
      "imdbRating": "7.6",
      "runtime": "40",
      "episode": "8"
    },
    {
      "type": "tvshows",
      "title": "Mágica Mortal",
      "permalink": "https://thefilmes.tv/series/84552-magica-mortal/",
      "category": "Reality",
      "imdb": "tt8887956",
      "poster": "https://image.tmdb.org/t/p/w300/ic8ANhZGZt04X8uB1pt3rTjVOZ1.jpg",
      "backdrop": "https://image.tmdb.org/t/p/w500/vp0guD91HsW94NglOAUAgG4P3Ur.jpg",
      "year": "2018",
      "imdbRating": "7.4",
      "runtime": "31",
      "episode": "8"
    },
    {
      "type": "tvshows",
      "title": "Ordem na Casa com Marie Kondo",
      "permalink": "https://thefilmes.tv/series/85202-ordem-na-casa-com-marie-kondo/",
      "category": "Reality",
      "imdb": "tt8115560",
      "poster": "https://image.tmdb.org/t/p/w300/9587sLgbOwAVbjcMKIOMA10Mfed.jpg",
      "backdrop": "https://image.tmdb.org/t/p/w500/kQmZJaO78iy64ZohqOzjNS6k6Ry.jpg",
      "year": "2019",
      "imdbRating": "7.1",
      "runtime": "40",
      "episode": "8"
    },
    {
      "type": "tvshows",
      "title": "Irmãs de Cela",
      "permalink": "https://thefilmes.tv/series/89295-irmas-de-cela/",
      "category": "Reality",
      "imdb": "tt10243628",
      "poster": "https://image.tmdb.org/t/p/w300/cymY9UQs6PoAhHQ5sLYIV9JzSz0.jpg",
      "backdrop": "https://image.tmdb.org/t/p/w500/wtgITCbWcoBhSAm79givbHgnZ89.jpg",
      "year": "2019",
      "imdbRating": "7.3",
      "runtime": "45",
      "episode": "6"
    },
    {
      "type": "tvshows",
      "title": "Funerária Família Bernard",
      "permalink": "https://thefilmes.tv/series/118111-funeraria-familia-bernard/",
      "category": "Reality",
      "imdb": "tt13848380",
      "poster": "https://image.tmdb.org/t/p/w300/zOUbP2SFUwb5n2E6ixEhpl0kc06.jpg",
      "backdrop": "https://image.tmdb.org/t/p/w500/gF9OoSwF22caE2ipuko4RCxQAWo.jpg",
      "year": "2021",
      "imdbRating": "2",
      "runtime": "",
      "episode": "8"
    },
    {
      "type": "tvshows",
      "title": "Adotada",
      "permalink": "https://thefilmes.tv/series/99223-adotada/",
      "category": "Comédia, Reality",
      "imdb": "tt4048998",
      "poster": "https://image.tmdb.org/t/p/w300/mGdbBFDWDPtcUNnadhErCw1wm5W.jpg",
      "backdrop": "https://image.tmdb.org/t/p/w500/b0j8Y90rEgpl0QnxIL2m7IpPIeA.jpg",
      "year": "2014",
      "imdbRating": "",
      "runtime": "50",
      "episode": "12"
    },
    {
      "type": "tvshows",
      "title": "Namoro, Amizade\u0026#8230; Ou Adeus?",
      "permalink": "https://thefilmes.tv/series/86807-namoro-amizade-ou-adeus/",
      "category": "Reality",
      "imdb": "tt9654080",
      "poster": "https://image.tmdb.org/t/p/w300/8Bylu6ne7GRLzdfKEDwWJNfZugP.jpg",
      "backdrop": "https://image.tmdb.org/t/p/w500/7o1w9s43hXdxr9AJAftGapSA4jy.jpg",
      "year": "2019",
      "imdbRating": "7",
      "runtime": "30",
      "episode": "6"
    },
    {
      "type": "tvshows",
      "title": "Grite, Você Está Sendo Filmado",
      "permalink": "https://thefilmes.tv/series/94515-grite-voce-esta-sendo-filmado/",
      "category": "Comédia, Reality",
      "imdb": "tt10487072",
      "poster": "https://image.tmdb.org/t/p/w300/bim1J1wpoUBCV6xsgz9ZsR0nOS2.jpg",
      "backdrop": "https://image.tmdb.org/t/p/w500/9ONBnYUJWvKVKVHE3e5pjN0G1OW.jpg",
      "year": "2019",
      "imdbRating": "7.3",
      "runtime": "25",
      "episode": "7"
    },
    {
      "type": "tvshows",
      "title": "Bling Empire",
      "permalink": "https://thefilmes.tv/series/116250-bling-empire/",
      "category": "Lançamento, Reality",
      "imdb": "tt13660962",
      "poster": "https://image.tmdb.org/t/p/w300/vY0m7PyZe3IeIqijFr6jRwYKMwk.jpg",
      "backdrop": "https://image.tmdb.org/t/p/w500/dXatJv3oNbuEgCzp1dVM91dLUiF.jpg",
      "year": "2021",
      "imdbRating": "10",
      "runtime": "",
      "episode": "8"
    },
    {
      "type": "tvshows",
      "title": "Game dos Clones",
      "permalink": "https://thefilmes.tv/series/111501-game-dos-clones/",
      "category": "Reality",
      "imdb": "tt13364038",
      "poster": "https://image.tmdb.org/t/p/w300/qVJB4EbYfRPB2UsHiGeVCzIZZrj.jpg",
      "backdrop": "https://image.tmdb.org/t/p/w500/rnPAtwW8vpHNDroSvOg2KsY7y6j.jpg",
      "year": "2020",
      "imdbRating": "9.5",
      "runtime": "50",
      "episode": "6"
    },
    {
      "type": "tvshows",
      "title": "Doenças do Século 21",
      "permalink": "https://thefilmes.tv/series/81521-doencas-do-seculo-21/",
      "category": "Documentário, Mistério, Reality, Talk",
      "imdb": "tt8792570",
      "poster": "https://image.tmdb.org/t/p/w300/wQL5YJq0348OxRgO14YxrlOy7dT.jpg",
      "backdrop": "https://image.tmdb.org/t/p/w500/qIYieR9t1CmEaBC2mNo0oYStkRE.jpg",
      "year": "2018",
      "imdbRating": "4.8",
      "runtime": "45",
      "episode": "7"
    },
    {
      "type": "tvshows",
      "title": "Life of Kylie",
      "permalink": "https://thefilmes.tv/series/71427-life-of-kylie/",
      "category": "Lançamento, Reality",
      "imdb": "tt6772826",
      "poster": "https://image.tmdb.org/t/p/w300/eAE42OlJdXzaNCekE0ww0KYOcAd.jpg",
      "backdrop": "https://image.tmdb.org/t/p/w500/doSfKKsBBVW20IEELEOifiI5mf7.jpg",
      "year": "2017",
      "imdbRating": "4.6",
      "runtime": "21",
      "episode": "8"
    },
    {
      "type": "tvshows",
      "title": "Piscou, Dançou",
      "permalink": "https://thefilmes.tv/series/89005-piscou-dancou/",
      "category": "Lançamento, Reality",
      "imdb": "tt9196244",
      "poster": "https://image.tmdb.org/t/p/w300/x4XmsoAY91wEyPH1DhEc1bAXLjb.jpg",
      "backdrop": "https://image.tmdb.org/t/p/w500/mkKfyqgzRJG1G6dFZ021H5V4M3x.jpg",
      "year": "2019",
      "imdbRating": "4.3",
      "runtime": "24",
      "episode": "10"
    },
    {
      "type": "tvshows",
      "title": "Largados e Pelados: A Tribo",
      "permalink": "https://thefilmes.tv/series/63451-largados-e-pelados-a-tribo/",
      "category": "Documentário, Reality",
      "imdb": "tt4791250",
      "poster": "https://image.tmdb.org/t/p/w300/vlJg6QLXqK1RrucEe72u9mHbuj2.jpg",
      "backdrop": "https://image.tmdb.org/t/p/w500/qkfC7uVEQ5RiPsGmNhFQ0uO1LK1.jpg",
      "year": "2015",
      "imdbRating": "9.5",
      "runtime": "60",
      "episode": "10"
    },
    {
      "type": "tvshows",
      "title": "Largados e Pelados",
      "permalink": "https://thefilmes.tv/series/58832-largados-e-pelados/",
      "category": "Reality",
      "imdb": "tt3007640",
      "poster": "https://image.tmdb.org/t/p/w300/6LSTSQ46Rxu0wmsNyqy0ge4qOaN.jpg",
      "backdrop": "https://image.tmdb.org/t/p/w500/epLA5w6NKzBGvpz8wvKQYygWkwf.jpg",
      "year": "2013",
      "imdbRating": "6.8",
      "runtime": "42",
      "episode": "25"
    },
    {
      "type": "tvshows",
      "title": "O Crush Perfeito",
      "permalink": "https://thefilmes.tv/series/105846-o-crush-perfeito/",
      "category": "Lançamento, Reality",
      "imdb": "tt12502140",
      "poster": "https://image.tmdb.org/t/p/w300/95wtmocCpz7ko9dQH3RYISrauqF.jpg",
      "backdrop": "https://image.tmdb.org/t/p/w500/1dNdNeBqcxsWK1MynwWGZIYGhQI.jpg",
      "year": "2020",
      "imdbRating": "",
      "runtime": "27",
      "episode": "6"
    },
    {
      "type": "tvshows",
      "title": "RuPaul\u0026#8217;s Drag Race",
      "permalink": "https://thefilmes.tv/series/8514-rupauls-drag-race/",
      "category": "Reality",
      "imdb": "tt1353056",
      "poster": "https://image.tmdb.org/t/p/w300/gPbHZ9Wc1K3ZjZZ03NFc2Jsi6sn.jpg",
      "backdrop": "https://image.tmdb.org/t/p/w500/u18xsYOYPDlQjs9kHNiY9zQ4GmG.jpg",
      "year": "2009",
      "imdbRating": "7.9",
      "runtime": "43",
      "episode": "14"
    },
    {
      "type": "tvshows",
      "title": "The Voice Brasil",
      "permalink": "https://thefilmes.tv/series/46299-the-voice-brasil/",
      "category": "Reality",
      "imdb": "tt2162116",
      "poster": "https://image.tmdb.org/t/p/w300/1bYuQAWIA2UFYrvShBv64zhdfDA.jpg",
      "backdrop": "https://image.tmdb.org/t/p/w500/3UuFsmTPAhT1N9Q4HFUZG7UBxQX.jpg",
      "year": "2012",
      "imdbRating": "10",
      "runtime": "90",
      "episode": ""
    },
    {
      "type": "tvshows",
      "title": "O Sócio",
      "permalink": "https://thefilmes.tv/series/62674-o-socio/",
      "category": "Reality",
      "imdb": "tt3080030",
      "poster": "https://image.tmdb.org/t/p/w300/vsPJxYYzxpSbPXfXfmSJO4GPOFu.jpg",
      "backdrop": "https://thefilmes.tv/wp-content/themes/mega_beta/assets/img/no/no_poster.png",
      "year": "2013",
      "imdbRating": "7.9",
      "runtime": "45",
      "episode": "12"
    },
    {
      "type": "tvshows",
      "title": "The Circle Brasil",
      "permalink": "https://thefilmes.tv/series/99620-the-circle-brasil/",
      "category": "Reality",
      "imdb": "tt9581782",
      "poster": "https://image.tmdb.org/t/p/w300/w0SInlIR3VS7MNVBVdh8J17S3od.jpg",
      "backdrop": "https://image.tmdb.org/t/p/w500/gluw8eJe9urjtxKjphCspQqlrrR.jpg",
      "year": "2020",
      "imdbRating": "10",
      "runtime": "",
      "episode": "4"
    },
    {
      "type": "tvshows",
      "title": "Restaurantes em Risco",
      "permalink": "https://thefilmes.tv/series/99864-restaurantes-em-risco/",
      "category": "Reality",
      "imdb": "tt8784324",
      "poster": "https://image.tmdb.org/t/p/w300/20I6eNGgJdag3h9oR8s7nC5vYJB.jpg",
      "backdrop": "https://image.tmdb.org/t/p/w500/oAeHS6HfL6UYg7ZTyTlVnjodDN1.jpg",
      "year": "2020",
      "imdbRating": "8",
      "runtime": "47",
      "episode": "6"
    },
    {
      "type": "tvshows",
      "title": "The Circle",
      "permalink": "https://thefilmes.tv/series/82450-the-circle/",
      "category": "Reality",
      "imdb": "tt8430234",
      "poster": "https://image.tmdb.org/t/p/w300/mhBC4NniNV3NJSb49Ttt1kmIFkA.jpg",
      "backdrop": "https://image.tmdb.org/t/p/w500/ht3WpaDPw7VKGfzaUnToM33IbI7.jpg",
      "year": "2018",
      "imdbRating": "8.3",
      "runtime": "45",
      "episode": "12"
    },
    {
      "type": "tvshows",
      "title": "Pesadelo na Cozinha",
      "permalink": "https://thefilmes.tv/series/69925-pesadelo-na-cozinha/",
      "category": "Reality",
      "imdb": "tt6526624",
      "poster": "https://image.tmdb.org/t/p/w300/8KA33hJQ8jCnjcs6bK6gjVTUUoj.jpg",
      "backdrop": "https://thefilmes.tv/wp-content/themes/mega_beta/assets/img/no/no_poster.png",
      "year": "2017",
      "imdbRating": "7",
      "runtime": "90",
      "episode": "7"
    },
    {
      "type": "tvshows",
      "title": "Carangas x Carrões",
      "permalink": "https://thefilmes.tv/series/78412-carangas-x-carroes/",
      "category": "Action \u0026amp; Adventure, Reality",
      "imdb": "tt8295694",
      "poster": "https://image.tmdb.org/t/p/w300/1adfueZfJIkiUAx6cFIs7fRA2uO.jpg",
      "backdrop": "https://image.tmdb.org/t/p/w500/k9ZbiUsCvpIQ7rWZ3eH0UBagTI9.jpg",
      "year": "2018",
      "imdbRating": "8",
      "runtime": "45",
      "episode": "7"
    },
    {
      "type": "tvshows",
      "title": "Hyperdrive",
      "permalink": "https://thefilmes.tv/series/91766-hyperdrive/",
      "category": "Reality",
      "imdb": "tt8911552",
      "poster": "https://image.tmdb.org/t/p/w300/2NMBLLwWYUpXWQp39L9MxC0iD00.jpg",
      "backdrop": "https://image.tmdb.org/t/p/w500/ieysZSBngaild6R825N7kFMDUiY.jpg",
      "year": "2019",
      "imdbRating": "8.1",
      "runtime": "48",
      "episode": "10"
    },
    {
      "type": "tvshows",
      "title": "Irmãos à Obra",
      "permalink": "https://thefilmes.tv/series/35058-irmaos-a-obra/",
      "category": "Reality",
      "imdb": "tt1827882",
      "poster": "https://image.tmdb.org/t/p/w300/ccggWzKxSao1VNaVFJNLkZG96Fb.jpg",
      "backdrop": "https://image.tmdb.org/t/p/w500/4yE7q1MwvM4JLlBH9WcmP2GY26l.jpg",
      "year": "2011",
      "imdbRating": "7.5",
      "runtime": "45",
      "episode": "18"
    },
    {
      "type": "tvshows",
      "title": "Cozinhando em 4:20",
      "permalink": "https://thefilmes.tv/series/80357-cooking-on-high/",
      "category": "Comédia, Reality",
      "imdb": "tt8521728",
      "poster": "https://image.tmdb.org/t/p/w300/cgIKvjs3oEh402wrwjjwUUZoawn.jpg",
      "backdrop": "https://image.tmdb.org/t/p/w500/ArZm90Y1z1FCvjOAPiGqjUwtcyY.jpg",
      "year": "2018",
      "imdbRating": "7.5",
      "runtime": "14",
      "episode": "12"
    },
    {
      "type": "tvshows",
      "title": "Vidrados",
      "permalink": "https://thefilmes.tv/series/91056-vidrados/",
      "category": "Reality",
      "imdb": "tt9908860",
      "poster": "https://image.tmdb.org/t/p/w300/9YmSm6x2aER6a7vfoOTDL9cKEuF.jpg",
      "backdrop": "https://image.tmdb.org/t/p/w500/h9mI2DX3rpySu6uavpvQvScaVX3.jpg",
      "year": "2019",
      "imdbRating": "6",
      "runtime": "24",
      "episode": "10"
    },
    {
      "type": "tvshows",
      "title": "Masterchef Brasil",
      "permalink": "https://thefilmes.tv/series/64203-masterchef-brasil/",
      "category": "Família, Reality",
      "imdb": "tt5037502",
      "poster": "https://image.tmdb.org/t/p/w300/84Ku5P8ISu3zQG0hC315WPjjsBx.jpg",
      "backdrop": "https://image.tmdb.org/t/p/w500/enjrpJS9CgoOdU2OpdajQCPsAai.jpg",
      "year": "2014",
      "imdbRating": "8",
      "runtime": "125",
      "episode": "22"
    },
    {
      "type": "tvshows",
      "title": "Eu Vi",
      "permalink": "https://thefilmes.tv/series/83247-eu-vi/",
      "category": "Documentário, Reality",
      "imdb": "tt9077192",
      "poster": "https://image.tmdb.org/t/p/w300/meGhL2jnUPwJt5vOjzIwSVhCIiC.jpg",
      "backdrop": "https://image.tmdb.org/t/p/w500/otvExbMrJyPUCvOZzhVsrDYEO1f.jpg",
      "year": "2018",
      "imdbRating": "7.1",
      "runtime": "25",
      "episode": "6"
    },
    {
      "type": "tvshows",
      "title": "The Titan Games",
      "permalink": "https://thefilmes.tv/series/85487-the-titan-games/",
      "category": "Reality",
      "imdb": "tt7967262",
      "poster": "https://image.tmdb.org/t/p/w300/nWq4WSjyWkv2a0QCpEylKbz7Q6t.jpg",
      "backdrop": "https://image.tmdb.org/t/p/w500/egNhPU9qJ9OkYKVsil5QWAX2BqS.jpg",
      "year": "2019",
      "imdbRating": "7.7",
      "runtime": "43",
      "episode": "9"
    },
    {
      "type": "tvshows",
      "title": "Pesca Implacável",
      "permalink": "https://thefilmes.tv/series/82498-pesca-implacavel/",
      "category": "Reality",
      "imdb": "tt8893566",
      "poster": "https://image.tmdb.org/t/p/w300/f05CT7h9xoGTRC5ixFT3KmmB0Sp.jpg",
      "backdrop": "https://image.tmdb.org/t/p/w500/8FXoAEbtEWw3MbHrqujNQF3JzzU.jpg",
      "year": "2018",
      "imdbRating": "8",
      "runtime": "45",
      "episode": "8"
    },
    {
      "type": "tvshows",
      "title": "Börü",
      "permalink": "https://thefilmes.tv/series/75365-boru-esquadrao-lobo/",
      "category": "Action \u0026amp; Adventure, Reality, War \u0026amp; Politics",
      "imdb": "tt7146600",
      "poster": "https://image.tmdb.org/t/p/w300/6xBjeBSzvhQhb97ln9PeodXxf6h.jpg",
      "backdrop": "https://image.tmdb.org/t/p/w500/iji4s0mBPxIdpzvYseKkK1JtpYx.jpg",
      "year": "2018",
      "imdbRating": "7.4",
      "runtime": "80",
      "episode": "6"
    },
    {
      "type": "tvshows",
      "title": "Mágica para a Humanidade",
      "permalink": "https://thefilmes.tv/series/81704-magica-para-a-humanidade/",
      "category": "Comédia, Reality",
      "imdb": "tt8425308",
      "poster": "https://image.tmdb.org/t/p/w300/vPdb9qbALBzMETT8rdBLyGdSEe2.jpg",
      "backdrop": "https://image.tmdb.org/t/p/w500/A2vgfcI3BClnmrhL2VkvcSCy7Qi.jpg",
      "year": "2018",
      "imdbRating": "6.7",
      "runtime": "25",
      "episode": "1"
    },
    {
      "type": "tvshows",
      "title": "60 Dias Infiltrados na Prisão",
      "permalink": "https://thefilmes.tv/series/65854-60-dias-infiltrados-na-prisao/",
      "category": "Documentário, Reality",
      "imdb": "tt5564124",
      "poster": "https://image.tmdb.org/t/p/w300/jvSGk5FKQov2AVPV3AU5zwSy7o2.jpg",
      "backdrop": "https://image.tmdb.org/t/p/w500/pTHFgf1EwlBoMV3bIqD0aLEdkDU.jpg",
      "year": "2016",
      "imdbRating": "6.4",
      "runtime": "45",
      "episode": "18"
    }
  ]
}